svarlr.py
svarlr-0.0.1.dist-info/LICENSE.txt
svarlr-0.0.1.dist-info/METADATA
svarlr-0.0.1.dist-info/WHEEL
svarlr-0.0.1.dist-info/top_level.txt
svarlr-0.0.1.dist-info/RECORD
