Metadata-Version: 2.1
Name: svarlr
Version: 0.0.1
Summary: A package to estimate structural vector autoregression models with a long-run restriction
Home-page: UNKNOWN
Author: Kyle Murphy
Author-email: kyleevanmurphy@gmail.com
License: UNKNOWN
Platform: UNKNOWN
Classifier: Programming Language :: Python :: 3
Classifier: License :: OSI Approved :: MIT License
Classifier: Operating System :: OS Independent
Requires-Python: >=3.6
